[{"UID": "0", "PID": "1", "system": "1.57", "CPUper": "1.74", "usr": "0.17", "Time": "07:03:55", "Command": "systemd", "CPU": "0", "guest": "0.00"}, {"UID": "0", "PID": "3", "system": "0.01", "CPUper": "0.01", "usr": "0.00", "Time": "07:03:55", "Command": "ksoftirqd/0", "CPU": "0", "guest": "0.00"}, {"UID": "0", "PID": "6", "system": "0.02", "CPUper": "0.02", "usr": "0.00", "Time": "07:03:55", "Command": "kworker/u4:0", "CPU": "0", "guest": "0.00"}, {"UID": "0", "PID": "7", "system": "0.10", "CPUper": "0.10", "usr": "0.00", "Time": "07:03:55", "Command": "rcu_sched", "CPU": "1", "guest": "0.00"}, {"UID": "0", "PID": "9", "system": "0.01", "CPUper": "0.01", "usr": "0.00", "Time": "07:03:55", "Command": "migration/0", "CPU": "0", "guest": "0.00"}, {"UID": "0", "PID": "10", "system": "0.00", "CPUper": "0.00", "usr": "0.00", "Time": "07:03:55", "Command": "watchdog/0", "CPU": "0", "guest": "0.00"}, {"UID": "0", "PID": "11", "system": "0.00", "CPUper": "0.00", "usr": "0.00", "Time": "07:03:55", "Command": "watchdog/1", "CPU": "1", "guest": "0.00"}, {"UID": "0", "PID": "12", "system": "0.01", "CPUper": "0.01", "usr": "0.00", "Time": "07:03:55", "Command": "migration/1", "CPU": "1", "guest": "0.00"}, {"UID": "0", "PID": "13", "system": "0.03", "CPUper": "0.03", "usr": "0.00", "Time": "07:03:55", "Command": "ksoftirqd/1", "CPU": "1", "guest": "0.00"}, {"UID": "0", "PID": "31", "system": "0.01", "CPUper": "0.01", "usr": "0.00", "Time": "07:03:55", "Command": "kworker/0:1", "CPU": "0", "guest": "0.00"}, {"UID": "0", "PID": "83", "system": "0.03", "CPUper": "0.03", "usr": "0.00", "Time": "07:03:55", "Command": "kworker/u4:2", "CPU": "0", "guest": "0.00"}, {"UID": "0", "PID": "261", "system": "0.02", "CPUper": "0.02", "usr": "0.00", "Time": "07:03:55", "Command": "kworker/0:2", "CPU": "0", "guest": "0.00"}, {"UID": "0", "PID": "714", "system": "0.01", "CPUper": "0.01", "usr": "0.00", "Time": "07:03:55", "Command": "jbd2/sda1-8", "CPU": "1", "guest": "0.00"}, {"UID": "0", "PID": "791", "system": "0.01", "CPUper": "0.06", "usr": "0.05", "Time": "07:03:55", "Command": "systemd-journal", "CPU": "0", "guest": "0.00"}, {"UID": "0", "PID": "852", "system": "0.01", "CPUper": "0.07", "usr": "0.06", "Time": "07:03:55", "Command": "systemd-udevd", "CPU": "0", "guest": "0.00"}, {"UID": "100", "PID": "1575", "system": "0.01", "CPUper": "0.01", "usr": "0.00", "Time": "07:03:55", "Command": "systemd-timesyn", "CPU": "1", "guest": "0.00"}, {"UID": "0", "PID": "1809", "system": "0.02", "CPUper": "0.02", "usr": "0.01", "Time": "07:03:55", "Command": "snapd", "CPU": "0", "guest": "0.00"}, {"UID": "0", "PID": "1811", "system": "0.00", "CPUper": "0.01", "usr": "0.00", "Time": "07:03:55", "Command": "systemd-logind", "CPU": "1", "guest": "0.00"}, {"UID": "107", "PID": "1813", "system": "0.01", "CPUper": "0.02", "usr": "0.01", "Time": "07:03:55", "Command": "dbus-daemon", "CPU": "1", "guest": "0.00"}, {"UID": "0", "PID": "1827", "system": "0.01", "CPUper": "0.01", "usr": "0.01", "Time": "07:03:55", "Command": "accounts-daemon", "CPU": "0", "guest": "0.00"}, {"UID": "104", "PID": "1835", "system": "0.01", "CPUper": "0.02", "usr": "0.00", "Time": "07:03:55", "Command": "rsyslogd", "CPU": "0", "guest": "0.00"}, {"UID": "0", "PID": "1866", "system": "0.00", "CPUper": "0.01", "usr": "0.00", "Time": "07:03:55", "Command": "polkitd", "CPU": "1", "guest": "0.00"}, {"UID": "0", "PID": "2116", "system": "0.00", "CPUper": "0.01", "usr": "0.01", "Time": "07:03:55", "Command": "sshd", "CPU": "0", "guest": "0.00"}, {"UID": "0", "PID": "2124", "system": "0.01", "CPUper": "0.01", "usr": "0.00", "Time": "07:03:55", "Command": "kworker/0:3", "CPU": "0", "guest": "0.00"}, {"UID": "0", "PID": "2132", "system": "0.01", "CPUper": "0.01", "usr": "0.00", "Time": "07:03:55", "Command": "iscsid", "CPU": "1", "guest": "0.00"}, {"UID": "0", "PID": "2133", "system": "0.03", "CPUper": "0.03", "usr": "0.00", "Time": "07:03:55", "Command": "iscsid", "CPU": "1", "guest": "0.00"}, {"UID": "0", "PID": "2192", "system": "0.00", "CPUper": "0.00", "usr": "0.00", "Time": "07:03:55", "Command": "agetty", "CPU": "0", "guest": "0.00"}, {"UID": "0", "PID": "2199", "system": "0.00", "CPUper": "0.00", "usr": "0.00", "Time": "07:03:55", "Command": "irqbalance", "CPU": "1", "guest": "0.00"}, {"UID": "0", "PID": "2303", "system": "0.00", "CPUper": "0.01", "usr": "0.01", "Time": "07:03:55", "Command": "sshd", "CPU": "0", "guest": "0.00"}, {"UID": "1000", "PID": "2305", "system": "0.00", "CPUper": "0.00", "usr": "0.00", "Time": "07:03:55", "Command": "systemd", "CPU": "1", "guest": "0.00"}, {"UID": "1000", "PID": "2341", "system": "0.01", "CPUper": "0.02", "usr": "0.00", "Time": "07:03:55", "Command": "sshd", "CPU": "0", "guest": "0.00"}, {"UID": "1000", "PID": "2342", "system": "0.01", "CPUper": "0.02", "usr": "0.01", "Time": "07:03:55", "Command": "bash", "CPU": "1", "guest": "0.00"}]